{
  "$schema": "https://json-schema.org/draft/2020-12/schema",
  "title": "Undergraduate Degrees",
  "description": "Undergraduate degrees offered at the University of Guelph",
  "type": "array",
  "items": {
    "type": "object",
    "properties": {
      "id": {
        "description": "A unique id for the degree",
        "type": "string"
      },
      "name": {
        "description": "The name of the degree",
        "type": "string"
      },
      "acronym": {
        "description": "A short name/acronym for the degree",
        "type": "string"
      },
      "url": {
        "description": "A URL to the degree page",
        "type": "string"
      },
      "tags": {
        "description": "Keywords used to improve the searchability of the degree",
        "type": "array",
        "items": {
          "type": "string"
        },
        "uniqueItems": true
      }
    },
    "patternProperties": {
      "^type$": {
        "description": "The associated type id for the degree",
        "type": "string"
      }
    },
    "required": ["id", "name", "type"],
    "additionalProperties": false
  }
}
